pop2net/__init__.py
pop2net/actor.py
pop2net/creator.py
pop2net/data_fakers/__init__.py
pop2net/data_fakers/soep/__init__.py
pop2net/data_fakers/soep/constants.py
pop2net/data_fakers/soep/soep_faker.py
pop2net/data_fakers/soep/soep_provider.py
pop2net/entity_list.py
pop2net/environment.py
pop2net/exceptions.py
pop2net/inspector.py
pop2net/location.py
pop2net/location_designer.py
pop2net/reader.py
pop2net/sequences.py
pop2net/utils.py
pop2net-1.2.2.dist-info/METADATA
pop2net-1.2.2.dist-info/WHEEL
pop2net-1.2.2.dist-info/licenses/LICENSE
pop2net-1.2.2.dist-info/RECORD
