Metadata-Version: 2.4
Name: pop2net
Version: 1.2.2
Summary: Pop2net is a Python package designed to generate and manage relations between agents in agent-based models in a simple and flexible way.
License: MIT
License-File: LICENSE
Author: Marius Kaffai
Author-email: marius.kaffai@sowi.uni-stuttgart.de
Requires-Python: >=3.11, !=2.7.*, !=3.0.*, !=3.1.*, !=3.2.*, !=3.3.*, !=3.4.*, !=3.5.*, !=3.6.*, !=3.7.*, !=3.8.*, !=3.9.*, !=3.10.*
Classifier: License :: OSI Approved :: MIT License
Classifier: Programming Language :: Python :: 3
Classifier: Programming Language :: Python :: 3.11
Classifier: Programming Language :: Python :: 3.12
Classifier: Programming Language :: Python :: 3.13
Classifier: Programming Language :: Python :: 3.14
Requires-Dist: bokehgraph (>=1.1.0,<2.0.0)
Requires-Dist: faker (>=15.1.1,<16.0.0)
Requires-Dist: mesa (>=3.1.5,<4.0.0)
Requires-Dist: numpy (>=1.26) ; python_version >= "3.12"
Requires-Dist: numpy (>=1.7) ; python_full_version <= "3.12.0"
Requires-Dist: pandas (>=1.5.1)
Requires-Dist: scipy (>=1.11.3) ; python_version >= "3.12"
Requires-Dist: scipy (>=1.6) ; python_full_version <= "3.12.0"
Requires-Dist: seaborn (>=0.12.1,<0.13.0)
Requires-Dist: tabulate (>=0.9.0,<0.10.0)
